megaqc/__init__.py
megaqc/app.py
megaqc/cli.py
megaqc/commands.py
megaqc/compat.py
megaqc/database.py
megaqc/extensions.py
megaqc/scheduler.py
megaqc/settings.py
megaqc/wsgi.py
megaqc/api/__init__.py
megaqc/api/constants.py
megaqc/api/utils.py
megaqc/api/views.py
megaqc/migrations/README
megaqc/migrations/alembic.ini
megaqc/migrations/env.py
megaqc/migrations/script.py.mako
megaqc/migrations/versions/007c354223ec_.py
megaqc/migrations/versions/4515f66f3690_.py
megaqc/migrations/versions/e38ef2ac89ab_.py
megaqc/migrations/versions/eb9fdf01bbae_.py
megaqc/model/__init__.py
megaqc/model/models.py
megaqc/public/__init__.py
megaqc/public/forms.py
megaqc/public/views.py
megaqc/report_plot/__init__.py
megaqc/report_plot/views.py
megaqc/rest_api/__init__.py
megaqc/rest_api/content.py
megaqc/rest_api/fields.py
megaqc/rest_api/filters.py
megaqc/rest_api/outlier.py
megaqc/rest_api/plot.py
megaqc/rest_api/schemas.py
megaqc/rest_api/utils.py
megaqc/rest_api/views.py
megaqc/rest_api/webarg_parser.py
megaqc/static/css/bootstrap.min.css
megaqc/static/css/component-chosen.min.css
megaqc/static/css/font-awesome.min.css
megaqc/static/css/gridstack.min.css
megaqc/static/css/main.css
megaqc/static/css/tether.min.css
megaqc/static/css/toastr.min.css
megaqc/static/fonts/FontAwesome.otf
megaqc/static/fonts/fontawesome-webfont.eot
megaqc/static/fonts/fontawesome-webfont.svg
megaqc/static/fonts/fontawesome-webfont.ttf
megaqc/static/fonts/fontawesome-webfont.woff
megaqc/static/fonts/fontawesome-webfont.woff2
megaqc/static/fonts/roboto/LICENSE.txt
megaqc/static/fonts/roboto/Roboto-Black.ttf
megaqc/static/fonts/roboto/Roboto-BlackItalic.ttf
megaqc/static/fonts/roboto/Roboto-Bold.ttf
megaqc/static/fonts/roboto/Roboto-BoldItalic.ttf
megaqc/static/fonts/roboto/Roboto-Italic.ttf
megaqc/static/fonts/roboto/Roboto-Light.ttf
megaqc/static/fonts/roboto/Roboto-LightItalic.ttf
megaqc/static/fonts/roboto/Roboto-Medium.ttf
megaqc/static/fonts/roboto/Roboto-MediumItalic.ttf
megaqc-0.2.0.dist-info/LICENSE
megaqc-0.2.0.dist-info/METADATA
megaqc-0.2.0.dist-info/WHEEL
megaqc-0.2.0.dist-info/entry_points.txt
megaqc-0.2.0.dist-info/top_level.txt
megaqc-0.2.0.dist-info/RECORD
